TrigFunc/__init__.py
TrigFunc/trig.py
TrigFunc-0.0.3.dist-info/LICENCE.txt
TrigFunc-0.0.3.dist-info/METADATA
TrigFunc-0.0.3.dist-info/WHEEL
TrigFunc-0.0.3.dist-info/top_level.txt
TrigFunc-0.0.3.dist-info/RECORD
