Metadata-Version: 2.1
Name: TrigFunc
Version: 0.0.3
Summary: Trigonomic functions package
Home-page: 
Author: 
Author-email: 
License: MIT
Keywords: calculator, trigonometry
Classifier: Development Status :: 5 - Production/Stable
Classifier: Intended Audience :: Education
Classifier: Operating System :: Microsoft :: Windows :: Windows 10
Classifier: License :: OSI Approved :: MIT License
Classifier: Programming Language :: Python :: 3
License-File: LICENCE.txt
